odoo_endpoints
